sloth_ci_ext_devtools.py
templates/extension.py
templates/validator.py
sloth_ci_ext_devtools-1.0.5.dist-info/LICENSE
sloth_ci_ext_devtools-1.0.5.dist-info/WHEEL
sloth_ci_ext_devtools-1.0.5.dist-info/METADATA
sloth_ci_ext_devtools-1.0.5.dist-info/RECORD
