Metadata-Version: 2.1
Name: sloth-ci-ext-devtools
Version: 1.0.5
Summary: Utilities to help you develop extensions and validators for Sloth CI
License: MIT
Author: Constantine Molchanov
Author-email: moigagoo@live.com
Requires-Python: >=3.9,<4.0
Classifier: License :: OSI Approved :: MIT License
Classifier: Programming Language :: Python :: 3
Classifier: Programming Language :: Python :: 3.9
Classifier: Programming Language :: Python :: 3.10
Requires-Dist: sloth-ci (>=2.2,<3.0)
